django_jupyter/__init__.py
django_jupyter/admin.py
django_jupyter/apps.py
django_jupyter/forms.py
django_jupyter/models.py
django_jupyter/tests.py
django_jupyter/views.py
django_jupyter/templatetags/__init__.py
django_jupyter/templatetags/jupyter_tags.py
django_jupyter-0.0.4.dist-info/METADATA
django_jupyter-0.0.4.dist-info/WHEEL
django_jupyter-0.0.4.dist-info/top_level.txt
django_jupyter-0.0.4.dist-info/RECORD
